README.md
setup.py
lbrlabs_pulumi_eks/__init__.py
lbrlabs_pulumi_eks/_utilities.py
lbrlabs_pulumi_eks/attached_node_group.py
lbrlabs_pulumi_eks/cluster.py
lbrlabs_pulumi_eks/iam_role_mapping.py
lbrlabs_pulumi_eks/iam_service_account_role.py
lbrlabs_pulumi_eks/provider.py
lbrlabs_pulumi_eks/pulumi-plugin.json
lbrlabs_pulumi_eks/py.typed
lbrlabs_pulumi_eks.egg-info/PKG-INFO
lbrlabs_pulumi_eks.egg-info/SOURCES.txt
lbrlabs_pulumi_eks.egg-info/dependency_links.txt
lbrlabs_pulumi_eks.egg-info/not-zip-safe
lbrlabs_pulumi_eks.egg-info/requires.txt
lbrlabs_pulumi_eks.egg-info/top_level.txt