Metadata-Version: 2.1
Name: lbrlabs-pulumi-eks
Version: 0.1.1a1694714386
Summary: A batteries included EKS cluster following best practices.
Home-page: UNKNOWN
License: UNKNOWN
Project-URL: Repository, https://github.com/lbrlabs/pulumi-lbrlabs-eks
Keywords: eks kubernetes aws lbrlabs kind/component category/cloud
Platform: UNKNOWN
Requires-Python: >=3.7
